{"dynamic_model": {"model_local_variables": [], "external_functions_temporary_terms_": [], "temporary_terms_": [], 
"residuals":[
{"residual": {"lhs": "1/c", "rhs": "beta*1/c(1)*(alpha*exp(a(1))*k^(alpha-1)*h(1)^(1-alpha)+1-delta)"}}
, {"residual": {"lhs": "c*gamma/(1-h)", "rhs": "(1-alpha)*exp(a)*k(-1)^alpha*h^(-alpha)"}}
, {"residual": {"lhs": "c+k-(1-delta)*k(-1)", "rhs": "exp(a)*k(-1)^alpha*h^(1-alpha)"}}
, {"residual": {"lhs": "y", "rhs": "exp(a)*k(-1)^alpha*h^(1-alpha)"}}
, {"residual": {"lhs": "i", "rhs": "y-c"}}
, {"residual": {"lhs": "a", "rhs": "rho*a(-1)+e"}}
, {"residual": {"lhs": "productivity", "rhs": "y/h"}}

]
, "external_functions_temporary_terms_jacobian": [], "temporary_terms_jacobian": [], "jacobian": {  "nrows": 7, "ncols": 13, "entries": [{"eq": 1, "col": 4, "var": "c", "shift": 0, "val": "(-1)/(c*c)"}
, {"eq": 1, "col": 10, "var": "c", "shift": 1, "val": "(-((alpha*exp(a(1))*k^(alpha-1)*h(1)^(1-alpha)+1-delta)*beta*(-1)/(c(1)*c(1))))"}
, {"eq": 1, "col": 5, "var": "k", "shift": 0, "val": "(-(beta*1/c(1)*h(1)^(1-alpha)*alpha*exp(a(1))*get_power_deriv(k,alpha-1,1)))"}
, {"eq": 1, "col": 11, "var": "h", "shift": 1, "val": "(-(beta*1/c(1)*alpha*exp(a(1))*k^(alpha-1)*get_power_deriv(h(1),1-alpha,1)))"}
, {"eq": 1, "col": 12, "var": "a", "shift": 1, "val": "(-(beta*1/c(1)*alpha*exp(a(1))*k^(alpha-1)*h(1)^(1-alpha)))"}
, {"eq": 2, "col": 4, "var": "c", "shift": 0, "val": "gamma/(1-h)"}
, {"eq": 2, "col": 1, "var": "k", "shift": -1, "val": "(-(h^(-alpha)*(1-alpha)*exp(a)*get_power_deriv(k(-1),alpha,1)))"}
, {"eq": 2, "col": 7, "var": "h", "shift": 0, "val": "c*gamma/((1-h)*(1-h))-(1-alpha)*exp(a)*k(-1)^alpha*get_power_deriv(h,(-alpha),1)"}
, {"eq": 2, "col": 8, "var": "a", "shift": 0, "val": "(-((1-alpha)*exp(a)*k(-1)^alpha*h^(-alpha)))"}
, {"eq": 3, "col": 4, "var": "c", "shift": 0, "val": "1"}
, {"eq": 3, "col": 1, "var": "k", "shift": -1, "val": "(-(1-delta))-h^(1-alpha)*exp(a)*get_power_deriv(k(-1),alpha,1)"}
, {"eq": 3, "col": 5, "var": "k", "shift": 0, "val": "1"}
, {"eq": 3, "col": 7, "var": "h", "shift": 0, "val": "(-(exp(a)*k(-1)^alpha*get_power_deriv(h,1-alpha,1)))"}
, {"eq": 3, "col": 8, "var": "a", "shift": 0, "val": "(-(exp(a)*k(-1)^alpha*h^(1-alpha)))"}
, {"eq": 4, "col": 3, "var": "y", "shift": 0, "val": "1"}
, {"eq": 4, "col": 1, "var": "k", "shift": -1, "val": "(-(h^(1-alpha)*exp(a)*get_power_deriv(k(-1),alpha,1)))"}
, {"eq": 4, "col": 7, "var": "h", "shift": 0, "val": "(-(exp(a)*k(-1)^alpha*get_power_deriv(h,1-alpha,1)))"}
, {"eq": 4, "col": 8, "var": "a", "shift": 0, "val": "(-(exp(a)*k(-1)^alpha*h^(1-alpha)))"}
, {"eq": 5, "col": 3, "var": "y", "shift": 0, "val": "(-1)"}
, {"eq": 5, "col": 4, "var": "c", "shift": 0, "val": "1"}
, {"eq": 5, "col": 6, "var": "i", "shift": 0, "val": "1"}
, {"eq": 6, "col": 2, "var": "a", "shift": -1, "val": "(-rho)"}
, {"eq": 6, "col": 8, "var": "a", "shift": 0, "val": "1"}
, {"eq": 6, "col": 13, "var": "e", "shift": 0, "val": "(-1)"}
, {"eq": 7, "col": 3, "var": "y", "shift": 0, "val": "(-(1/h))"}
, {"eq": 7, "col": 7, "var": "h", "shift": 0, "val": "(-((-y)/(h*h)))"}
, {"eq": 7, "col": 9, "var": "productivity", "shift": 0, "val": "1"}
]}, "external_functions_temporary_terms_hessian": [], "temporary_terms_hessian": [], "hessian": {  "nrows": 7, "ncols": 169, "entries": []}, "external_functions_temporary_terms_third_derivative": [], "temporary_terms_third_derivative": [], "third_derivative": {  "nrows": 7, "ncols": 2197, "entries": []}}}